bamboo/__init__.py
bamboo/api/__init__.py
bamboo/api/base.py
bamboo/api/form.py
bamboo/api/json.py
bamboo/app.py
bamboo/asgi.py
bamboo/cli/__init__.py
bamboo/cli/cli.py
bamboo/cli/static.py
bamboo/endpoint.py
bamboo/error.py
bamboo/http.py
bamboo/io.py
bamboo/location.py
bamboo/request/__init__.py
bamboo/request/ahttp.py
bamboo/request/ahttps.py
bamboo/request/http.py
bamboo/request/https.py
bamboo/request/request_form.py
bamboo/request/response.py
bamboo/router.py
bamboo/sticky/__init__.py
bamboo/sticky/http.py
bamboo/test.py
bamboo/util/__init__.py
bamboo/util/aio.py
bamboo/util/convert.py
bamboo/util/deco.py
bamboo/util/header.py
bamboo/util/path.py
bamboo/util/string.py
bamboo/util/time.py
bamboo/util/typing.py
bamboo_core-0.10.5.dist-info/entry_points.txt
bamboo_core-0.10.5.dist-info/LICENSE
bamboo_core-0.10.5.dist-info/WHEEL
bamboo_core-0.10.5.dist-info/METADATA
bamboo_core-0.10.5.dist-info/RECORD
