Metadata-Version: 2.1
Name: bamboo-core
Version: 0.10.5
Summary: General purpose server framework in Python
Home-page: https://jjj999.github.io/bamboo
License: MIT
Author: jjj999
Author-email: jjj999to@gmail.com
Maintainer: jjj999
Maintainer-email: jjj999to@gmail.com
Requires-Python: >=3.7,<4.0
Classifier: Development Status :: 4 - Beta
Classifier: Environment :: Web Environment
Classifier: Intended Audience :: Developers
Classifier: License :: OSI Approved :: MIT License
Classifier: Programming Language :: Python
Classifier: Programming Language :: Python :: 3
Classifier: Programming Language :: Python :: 3.10
Classifier: Programming Language :: Python :: 3.7
Classifier: Programming Language :: Python :: 3.8
Classifier: Programming Language :: Python :: 3.9
Classifier: Topic :: Internet :: WWW/HTTP :: Dynamic Content
Classifier: Topic :: Internet :: WWW/HTTP :: WSGI
Classifier: Topic :: Internet :: WWW/HTTP :: WSGI :: Application
Classifier: Topic :: Software Development :: Libraries :: Application Frameworks
Project-URL: Repository, https://github.com/jjj999/bamboo
